dexcomapi/__init__.py
dexcomapi-0.4.5.dist-info/LICENSE
dexcomapi-0.4.5.dist-info/METADATA
dexcomapi-0.4.5.dist-info/WHEEL
dexcomapi-0.4.5.dist-info/top_level.txt
dexcomapi-0.4.5.dist-info/RECORD
