Metadata-Version: 2.1
Name: dexcomapi
Version: 0.4.5
Summary: Uses Dexcom APIs to download blood glucose data
Home-page: https://github.com/jpw1012/dexcomapi
Author: Jim Walsh
Author-email: jim@walshfamily.email
License: UNKNOWN
Platform: UNKNOWN
Classifier: Programming Language :: Python :: 3
Classifier: License :: OSI Approved :: MIT License
Classifier: Operating System :: OS Independent
Requires-Python: >=3.6
